{
  "n_class": 5,
  "output_mode": "many",
  "eval_output_mode": "many",
  "type": "modulo_net",
  "encoders": {
    "eeg": {
      "type": "SimpleSleepNetEpochEncoderWithoutFrequencyReduction",
      "args": {
        "hidden_layers": 25,
        "dropout": 0.5,
        "bidir": true
      }
    }
  },
  "reducer": {
    "type": "AttentionReducer",
    "args": {
      "context_size": 25
    }
  },
  "features_encoder": {
    "type": "FullyConnected",
    "args": {
      "layers": [
        5
      ]
    }
  },
  "sequence_encoder": {
    "type": "ResidualGRUSequenceEncoder",
    "args": {
      "cells": 25,
      "dropout": 0.5,
      "bidir": true,
      "layers": 2
    }
  }
}